Workbook

Sheet Portfolio
A1: Stock | B1: Qty | C1: Avg Price | D1: LTP | E1: Investment | F1: Current Value | G1: Return % | H1: Insight
A2: GAIL | B2: 47 | C2: 198.52 | D2: 137.19 | E2: =B2*C2 -> 9330.44 | F2: =B2*D2 -> 6447.93
A3: RELIANCE | B3: 1 | C3: 1165 | D3: 1220 | E3: =B3*C3 -> 1165 | F3: =B3*D3 -> 1220
A4: ONGC | B4: 2 | C4: 219 | D4: 235 | E4: =B4*C4 -> 438 | F4: =B4*D4 -> 470
A5: IOC | B5: 3 | C5: 129.32 | D5: 135 | E5: =B5*C5 -> 387.96 | F5: =B5*D5 -> 405

Sheet Diversification
A1: Asset Name | B1: Type (Stock/Mutual Fund) | C1: Quantity/Units | D1: Price/NAV | E1: Value | F1: Allocation % | G1: Category | H1: Target Allocation % | I1: Difference | J1: Action | K1: Amount to Buy/Sell
A2: GAIL | B2: Stock | C2: 47 | D2: 137 | E2: =C2*D2 -> 6439 | F2: =E2/$E$6 -> 0.082362271 | G2: Energy | H2: 0.2 | I2: =F2-H2 -> -0.11763773 | J2: =IF(I2>0.05,"Sell",IF(I2<-0.05,"Buy","Hold")) -> Buy | K2: =(H2*$E$6)-E2 -> 9196.8
A3: RELIANCE | B3: Stock | C3: 1 | D3: 2900 | E3: =C3*D3 -> 2900 | F3: =E3/$E$6 -> 0.03709436 | G3: Conglomerate | H3: 0.2 | I3: =F3-H3 -> -0.16290564 | J3: =IF(I3>0.05,"Sell",IF(I3<-0.05,"Buy","Hold")) -> Buy | K3: =(H3*$E$6)-E3 -> 12735.8
A4: PPFAS | B4: Mutual Fund | C4: 120 | D4: 32 | E4: =C4*D4 -> 3840 | F4: =E4/$E$6 -> 0.04911805 | G4: Flexi Cap | H4: 0.2 | I4: =F4-H4 -> -0.15088195 | J4: =IF(I4>0.05,"Sell",IF(I4<-0.05,"Buy","Hold")) -> Buy | K4: =(H4*$E$6)-E4 -> 11795.8
A5: HDFC Large Cap | B5: Mutual Fund | C5: 50 | D5: 1300 | E5: =C5*D5 -> 65000 | F5: =E5/$E$6 -> 0.83142532 | G5: Large Cap | H5: 0.2 | I5: =F5-H5 -> 0.63142532 | J5: =IF(I5>0.05,"Sell",IF(I5<-0.05,"Buy","Hold")) -> Sell | K5: =(H5*$E$6)-E5 -> -49364.2
C6: Total | E6: =SUM(E2:E5) -> 78179
B11: 88% in Mutual Funds and 12% in Equity

Sheet Goal Planner
A1: Target Amount | B1: 5000000
A2: Years | B2: 10
A3: Expected Returns (%) | B3: 0.12
A4: Months | B4: =B2*12 -> 120
A5: Monthly Returns | B5: =B3/12 -> 0.01
A6: SIP Calculation | B6: =PMT(B5,B4,0,-B1) -> 21735.474
E10: Must invest 20k rupees to reach 50L in 10 Years.

Sheet Portfolio Risk
A1: Stock | B1: Weight | C1: Return | D1: Volatility
A2: GAIL | B2: 0.4 | C2: 0.1 | D2: 0.15
A3: RELIANCE | B3: 0.3 | C3: 0.12 | D3: 0.18
A4: ONGC | B4: 0.2 | C4: 0.08 | D4: 0.12
A5: IOC | B5: 0.1 | C5: 0.07 | D5: 0.1
A7: Portfolio Return | C7: =SUMPRODUCT(B2:B5,C2:C5) -> 0.099
A8: Portfolio Risk | C8: =SQRT(SUMPRODUCT((B2:B5^2),(D2:D5^2))) -> 0.08480566

Sheet Correlation
B1: GAIL.NS | C1: RELIANCE.NS | D1: ONGC.NS | E1: IOC.NS
A2: GAIL.NS | B2: 1 | C2: -0.1347567 | D2: -0.0012630325 | E2: 0.013035405
A3: RELIANCE.NS | B3: -0.1347567 | C3: 1 | D3: 0.2012726 | E3: 0.36623808
A4: ONGC.NS | B4: -0.0012630325 | C4: 0.2012726 | D4: 1 | E4: 0.23755037 | J4: Best Diversification | L4: Good Diversification | N4: Moderate Correlation | P4: Higher Side
A5: IOC.NS | B5: 0.013035405 | C5: 0.36623808 | D5: 0.23755037 | E5: 1 | J5: GAIL vs RELIANCE -> 0.13 | L5: GAIL vs ONGC --> 0.00 GAIL vs IOC --> 0.01 | N5: RELIANCE vs ONGC --> 0.20 ONGC vs IOC --> 0.24 | P5: RELIANCE vs IOC --> 0.37
J6: Slight nrgative correlation | L6: Almost no relationship | N6: Slightly related | P6: Starting to move together
J7: They move differently
J9: Meaning | L9: Meaning | N9: Meaning | P9: Meaning
J10: When one fails --> other may not | L10: Independent movement | N10: Not bad, Not great | P10: Not great diversification
J11: Portfolio becomes stable | L11: Strong diversification | P11: Both may fall together
J16: Interpretation
J18: Portfolio shows good diversification GAIL has low to negative correlation with other stocks, improving stability. ONGC and IOC have moderate correlation with RELIANCE, indicating some sector linkage. Overall, no high correlation pairs (>0.7), suggesting reduced risk from diversification. Portfolio is balanced but can be improved by adding more negatively correlated assets.

Sheet Dashboard
B3: Portfolio Dashboard
C7: Total Investment | D7: =SUM(D12:D15) -> 11321.4
C8: Current Value | D8: =SUM(Portfolio!F2:F5) -> 8542.93
C9: Return % | D9: =(D8/D7)-1 -> -0.24541753
C11: Stock | D11: Investment | E11: Current Value | F11: Return %
C12: =Portfolio!A2 -> GAIL | D12: =Portfolio!E2 -> 9330.44 | E12: =Portfolio!F2 -> 6447.93 | F12: =(E12/D12)-1 -> -0.30893613
C13: =Portfolio!A3 -> RELIANCE | D13: =Portfolio!E3 -> 1165 | E13: =Portfolio!F3 -> 1220 | F13: =(E13/D13)-1 -> 0.0472103
C14: =Portfolio!A4 -> ONGC | D14: =Portfolio!E4 -> 438 | E14: =Portfolio!F4 -> 470 | F14: =(E14/D14)-1 -> 0.073059361
C15: =Portfolio!A5 -> IOC | D15: =Portfolio!E5 -> 387.96 | E15: =Portfolio!F5 -> 405 | F15: =(E15/D15)-1 -> 0.043922054
C18: Portfolio Risk | D18: ='Portfolio Risk'!C8 -> 0.08480566
C19: Portfolio Return | D19: ='Portfolio Risk'!C7 -> 0.099
C22: Best Performer | D22: =INDEX(C12:C15,MATCH(MAX(F12:F15),F12:F15,0)) & " (" & TEXT(MAX(F12:F15),"0.0%") & ")" -> ONGC (7.3%)
C23: Worst Performer | D23: =INDEX(C12:C15,MATCH(MIN(F12:F15),F12:F15,0))& " (" & TEXT(MIN(F12:F15),"0.0%") & ")" -> GAIL (-30.9%)
